{
  "mcpServers": {
    "spring-micro-context": {
      "command": "node",
      "args": [
        "C:\\Projects\\CodyMcpServers\\packages\\micro-context\\dist\\index.js",
        "${workspaceFolder}"
      ],
      "env": {
        "PACKAGE_INCLUDE": "",
        "PACKAGE_EXCLUDE": "",
        "MCP_LOGGING": "true",
        "MCP_DEBUG": "false"
      }
    },
    "spring-macro-context": {
      "command": "node",
      "args": [
        "C:\\Projects\\CodyMcpServers\\packages\\macro-context\\dist\\index.js",
        "${workspaceFolder}"
      ],
      "env": {
        "PACKAGE_INCLUDE": "",
        "PACKAGE_EXCLUDE": "",
        "CALL_CHAIN_MAX_DEPTH": "15",
        "STOP_AT_PACKAGES": "java.*,javax.*,org.springframework.*,org.hibernate.*",
        "MCP_LOGGING": "true",
        "MCP_DEBUG": "false"
      }
    },
    "spring-component": {
      "command": "node",
      "args": [
        "C:\\Projects\\CodyMcpServers\\packages\\spring-component\\dist\\index.js",
        "${workspaceFolder}"
      ],
      "env": {
        "PACKAGE_INCLUDE": "",
        "PACKAGE_EXCLUDE": "",
        "MCP_LOGGING": "true",
        "MCP_DEBUG": "false"
      }
    }
  }
}
